drawmatrix/__init__.py
drawmatrix/drawmatrix.py
matrixdraw-0.0.1.dist-info/METADATA
matrixdraw-0.0.1.dist-info/WHEEL
matrixdraw-0.0.1.dist-info/top_level.txt
matrixdraw-0.0.1.dist-info/RECORD
