Metadata-Version: 2.1
Name: matrixdraw
Version: 0.0.1
Summary: Allows you to draw beautiful matrices.
Home-page: https://github.com/ko4nev812/draw-matrix
Author: konev_runk
Project-URL: GitHub, https://github.com/ko4nev812/draw-matrix
Keywords: draw matrix 2d 2d_matrix
Classifier: Programming Language :: Python :: 3.11
Classifier: License :: OSI Approved :: MIT License
Classifier: Operating System :: OS Independent
Requires-Python: >=3.6
